{
  "utenti": [
    {
      "id": 1,
      "nome": "Dario",
      "tipologia": "superuser"
    },
    {
      "id": 2,
      "nome": "Milo",
      "tipologia": "superuser"
    },
    {
      "id": 3,
      "nome": "Mauro",
      "tipologia": "superuser"
    }
  ],
  "studenti": [
    {
      "nome": "Anna",
      "tipologia": "studente",
      "id": 2
    },
    {
      "nome": "Prova",
      "tipologia": "studente",
      "id": 3
    },
    {
      "nome": "dario",
      "tipologia": "studente",
      "id": 4
    }
  ],
  "creator": {
    "nome": "Dario",
    "cognome": "Mennillo",
    "ruolo": "docente"
  }
}